<?xml version="1.0" ?><user-data><users><user><firstName>Arfa</firstName><lastName>Tahang</lastName><username>1</username><email>mandikatahang@gmail.com</email><password>1</password><userType>Pengguna Umum</userType><profilePicturePath>C:\Users\mandi\.CalmifyApp\profile_images\1.jpg</profilePicturePath><phoneNumber>08116850502</phoneNumber><bio>Siapakah diri anda</bio><totalPoints>0</totalPoints><activityHistory></activityHistory><recoveryCodes><string>V70AZJO3</string><string>6N8756F0</string></recoveryCodes><shareData>false</shareData><address>Jakal 14</address><country>Indonesia</country><city>Jogja</city><postalCode>123</postalCode></user><user><firstName>2</firstName><lastName>2</lastName><username>2</username><email>2</email><password>2</password><userType>Psikolog</userType><phoneNumber></phoneNumber><bio></bio><totalPoints>0</totalPoints><activityHistory></activityHistory><recoveryCodes><string>TDG4SB5Z</string><string>9L9X4MXG</string></recoveryCodes><shareData>false</shareData><address></address><country></country><city></city><postalCode></postalCode></user><user><firstName>3</firstName><lastName>3</lastName><username>3</username><email>3</email><password>3</password><userType>Pengguna Umum</userType><phoneNumber></phoneNumber><bio></bio><totalPoints>0</totalPoints><activityHistory></activityHistory><recoveryCodes><string>WK1SGWC4</string><string>PRFM89NS</string></recoveryCodes><shareData>false</shareData><address></address><country></country><city></city><postalCode></postalCode></user></users></user-data>